print_versions/__init__.py
print_versions/versions.py
print_versions-0.1.0.dist-info/METADATA
print_versions-0.1.0.dist-info/WHEEL
print_versions-0.1.0.dist-info/licenses/LICENSE
print_versions-0.1.0.dist-info/RECORD
