Metadata-Version: 2.1
Name: print_versions
Version: 0.1.0
Summary: Package for listing versions of python packages used in a Jupyter notebook.
Project-URL: Homepage, https://github.com/TimPchelintsev/print_versions
Project-URL: Issues, https://github.com/TimPchelintsev/print_versions/issues
Author-email: Timofey Pchelintsev <tpchelintsev@gmail.com>
License-File: LICENSE
Classifier: License :: OSI Approved :: MIT License
Classifier: Operating System :: OS Independent
Classifier: Programming Language :: Python :: 3
Requires-Python: >=3.8
